jux/__init__.py
jux/create_df_minmax.py
jux/denoise.py
jux/false_positive_detection.py
jux/file_handler.py
jux/flare_detect_minmax.py
jux/flare_detect_thresh.py
jux/helper.py
jux/jux.py
jux/params.py
jux/version.py
Jux-0.0.3.dist-info/METADATA
Jux-0.0.3.dist-info/WHEEL
Jux-0.0.3.dist-info/top_level.txt
Jux-0.0.3.dist-info/RECORD
