Metadata-Version: 2.1
Name: Jux
Version: 0.0.3
Summary: X-RAY Flare Burst Deterministic Detection
Home-page: UNKNOWN
Author: Team 10
License: UNKNOWN
Platform: UNKNOWN
Requires-Dist: astropy
Requires-Dist: numpy
Requires-Dist: pandas
Requires-Dist: matplotlib
Requires-Dist: scipy
Requires-Dist: plotly
Requires-Dist: sklearn
